llmcontext.py
repo_to_llm_context-2.2.6.dist-info/METADATA
repo_to_llm_context-2.2.6.dist-info/WHEEL
repo_to_llm_context-2.2.6.dist-info/entry_points.txt
repo_to_llm_context-2.2.6.dist-info/top_level.txt
repo_to_llm_context-2.2.6.dist-info/RECORD
