Metadata-Version: 2.4
Name: repo-to-llm-context
Version: 2.2.6
Summary: A tool to gather project context into a single file for LLMs
Author-email: Yigit Konur <yigit35@gmail.com>
License-Expression: MIT
Project-URL: Homepage, https://github.com/yigitkonur/code-to-clipboard-for-llms
Project-URL: Repository, https://github.com/yigitkonur/code-to-clipboard-for-llms
Project-URL: Issues, https://github.com/yigitkonur/code-to-clipboard-for-llms/issues
Keywords: llm,context,code,clipboard,ai,developer-tools
Classifier: Development Status :: 5 - Production/Stable
Classifier: Intended Audience :: Developers
Classifier: Operating System :: OS Independent
Classifier: Programming Language :: Python :: 3
Classifier: Programming Language :: Python :: 3.6
Classifier: Programming Language :: Python :: 3.7
Classifier: Programming Language :: Python :: 3.8
Classifier: Programming Language :: Python :: 3.9
Classifier: Programming Language :: Python :: 3.10
Classifier: Programming Language :: Python :: 3.11
Classifier: Programming Language :: Python :: 3.12
Classifier: Topic :: Software Development :: Libraries :: Python Modules
Classifier: Topic :: Text Processing :: Markup :: Markdown
Classifier: Topic :: Utilities
Requires-Python: >=3.6
Requires-Dist: pyperclip>=1.8.0
Requires-Dist: gitignore-parser>=0.1.0
Provides-Extra: dev
Requires-Dist: pytest>=6.0; extra == "dev"
Requires-Dist: black>=22.0; extra == "dev"
Requires-Dist: isort>=5.0; extra == "dev"
Requires-Dist: mypy>=0.900; extra == "dev"
